{"skeleton":{"hash":"JiDmfJFFpCZ9IqQQhrUnYB2Dgm0","spine":"3.8.84","x":-110.9,"y":-130.76,"width":218.82,"height":274.53},"bones":[{"name":"root","scaleX":0.8276,"scaleY":0.8276},{"name":"9","parent":"root"},{"name":"CLIP","parent":"9"},{"name":"flare","parent":"9","rotation":35,"x":-87.64,"y":129.35,"scaleX":28.2571,"scaleY":3.8999},{"name":"star1","parent":"9","x":-59.99,"y":100.71},{"name":"star2","parent":"9","x":-1.7,"y":34.56},{"name":"star3","parent":"9","x":56.4,"y":-84.99}],"slots":[{"name":"CLIP","bone":"CLIP","attachment":"CLIP"},{"name":"9","bone":"9","attachment":"10"},{"name":"flare","bone":"flare","color":"ffffff7a","attachment":"flare","blend":"additive"},{"name":"star3","bone":"star3","color":"906b9dff","attachment":"star1","blend":"additive"},{"name":"star2","bone":"star2","color":"906b9dff","attachment":"star1","blend":"additive"},{"name":"star1","bone":"star1","color":"906c9dff","attachment":"star1","blend":"additive"}],"skins":[{"name":"default","attachments":{"9":{"10":{"width":266,"height":266}},"CLIP":{"CLIP":{"type":"clipping","end":"flare","vertexCount":99,"vertices":[-123.75,76.85,-65.32,107.73,-49.98,116.37,-45.23,115.08,-45.59,104.18,-48.06,66.89,-48.99,23.88,-29.42,22.55,-24.15,40.58,-18.84,51.66,-9.95,66.4,-0.9,77.94,10.02,87.77,23.9,99.24,37.16,108.05,46.29,117.33,49.87,121.08,54.09,116.24,64.62,105.63,76.63,96.27,88.95,84.73,99.72,72.56,112.2,52.83,119.61,33.8,123.27,18.66,124.06,3.13,90.13,1.48,87.63,17.81,82.95,30.36,76.24,42.22,68.44,51.11,59.16,59.38,50.65,64.45,42,70.07,35.52,72.72,28.27,69.99,18.52,62.97,11.19,54.86,4.56,42.92,-0.12,29.04,-1.84,15.62,-2,1.25,-0.05,-10.99,3.85,-23.01,10.09,-36.27,17.66,-47.26,25.69,-56.16,33.18,-63.1,41.92,-69.26,51.28,-73.55,56.5,-73.78,64.85,-68.4,74.99,-57.79,82.4,-46.8,87.31,-34.55,89.5,-24.96,90.67,-13.41,90.9,-3.97,90.12,1.49,124.04,3.13,123.35,-11.85,120.7,-26.36,115,-41.73,109.39,-54.67,101.9,-66.14,92.85,-78,82.09,-88.68,71.32,-98.35,60.25,-107.17,49.09,-115.05,41.61,-119.41,35.91,-115.36,29.59,-110.44,18.21,-101.4,3.78,-86.97,-7.77,-71.05,-20.09,-49.37,-26.1,-33.61,-30.7,-15.91,-31.17,-0.39,-30.62,16.31,-29.45,22.55,-48.95,23.87,-49.03,-21.45,-47.48,-101.29,-46.85,-110.02,-61.91,-113.97,-82.03,-120.21,-87.1,-110.38,-83.43,-90.72,-80.55,-58.66,-79.14,-24.66,-79.38,13.56,-80.24,51.55,-81.48,63.01,-91.62,63.33,-102.7,64.42,-113.78,67.07,-119.24,73.08]}},"flare":{"flare":{"width":14,"height":14}},"star1":{"star1":{"width":148,"height":146}},"star2":{"star1":{"width":148,"height":146}},"star3":{"star1":{"width":148,"height":146}}}}],"animations":{"win":{"slots":{"flare":{"color":[{"color":"ffffff7a","curve":"stepped"},{"time":0.1667,"color":"ffffff7a"},{"time":0.4333,"color":"906b9dff","curve":"stepped"},{"time":0.7333,"color":"906b9dff"},{"time":0.9333,"color":"ffffff00"},{"time":1.6667,"color":"ffffff7a"},{"time":1.8333,"color":"906b9dff","curve":"stepped"},{"time":1.9667,"color":"906b9dff"},{"time":2.1,"color":"b1ffd579"},{"time":2.1667,"color":"906b9dff"},{"time":2.4,"color":"5e7335ae"},{"time":2.5667,"color":"ffffff00"},{"time":3.3333,"color":"ffffff7a"}]}},"bones":{"flare":{"translate":[{"curve":"stepped"},{"time":0.1667},{"time":1,"x":230.46,"y":-253.31,"curve":"stepped"},{"time":1.6667,"x":230.46,"y":-253.31},{"time":1.8333,"x":177.09,"y":-177.09},{"time":2.6667,"curve":"stepped"},{"time":3.3333}],"scale":[{"x":0.561,"y":0.561,"curve":"stepped"},{"time":0.1667,"x":0.561,"y":0.561},{"time":0.2667,"x":1.084,"y":0.714},{"time":0.3333,"x":1.583,"y":1.317},{"time":0.5,"x":2.833,"y":1.112},{"time":0.7333,"x":1.134,"y":1.269},{"time":1.6667,"x":0.908,"y":0.908},{"time":1.8333,"x":0.908,"y":2.307},{"time":2.1,"x":1.509,"y":0.533},{"time":2.2667,"y":2.335},{"time":2.5,"x":0.561,"y":0.561,"curve":"stepped"},{"time":3.3333,"x":0.561,"y":0.561}]},"star1":{"rotate":[{"curve":"stepped"},{"time":0.1667},{"time":0.5,"angle":45},{"time":3.3333}],"scale":[{"x":0,"y":0,"curve":"stepped"},{"time":0.1667,"x":0,"y":0},{"time":0.3333},{"time":0.5,"x":0,"y":0,"curve":"stepped"},{"time":2.3333,"x":0,"y":0},{"time":2.5},{"time":2.6667,"x":0,"y":0,"curve":"stepped"},{"time":3.3333,"x":0,"y":0}]},"star2":{"rotate":[{"curve":"stepped"},{"time":0.1667,"curve":"stepped"},{"time":0.4333},{"time":0.7667,"angle":-45},{"time":3.3333}],"scale":[{"x":0,"y":0,"curve":"stepped"},{"time":0.1667,"x":0,"y":0,"curve":"stepped"},{"time":0.4333,"x":0,"y":0},{"time":0.6},{"time":0.7667,"x":0,"y":0,"curve":"stepped"},{"time":2.0667,"x":0,"y":0},{"time":2.2333},{"time":2.4,"x":0,"y":0,"curve":"stepped"},{"time":3.3333,"x":0,"y":0}]},"star3":{"rotate":[{"curve":"stepped"},{"time":0.1667,"curve":"stepped"},{"time":0.6667},{"time":1,"angle":45},{"time":3.3333}],"scale":[{"x":0,"y":0,"curve":"stepped"},{"time":0.1667,"x":0,"y":0,"curve":"stepped"},{"time":0.6667,"x":0,"y":0},{"time":0.8333},{"time":1,"x":0,"y":0,"curve":"stepped"},{"time":1.6333,"x":0,"y":0,"curve":"stepped"},{"time":1.8,"x":0,"y":0},{"time":1.9667},{"time":2.1333,"x":0,"y":0,"curve":"stepped"},{"time":3.3333,"x":0,"y":0}]},"9":{"scale":[{},{"time":0.3333,"x":1.1,"y":1.1},{"time":1.6667},{"time":2,"x":1.1,"y":1.1},{"time":3.3333}]}}}}}